printwell/__init__.py
printwell/__init__.pyi
printwell/_native.cpython-312-x86_64-linux-gnu.so
printwell/py.typed
printwell.libs/libprintwell_native-7461f214.so
printwell-0.1.11.dist-info/METADATA
printwell-0.1.11.dist-info/WHEEL
printwell-0.1.11.dist-info/RECORD
