Metadata-Version: 2.4
Name: printwell
Version: 0.1.11
Classifier: Development Status :: 4 - Beta
Classifier: Intended Audience :: Developers
Classifier: License :: OSI Approved :: GNU Affero General Public License v3
Classifier: Programming Language :: Python :: 3
Classifier: Programming Language :: Python :: 3.9
Classifier: Programming Language :: Python :: 3.10
Classifier: Programming Language :: Python :: 3.11
Classifier: Programming Language :: Python :: 3.12
Classifier: Programming Language :: Python :: 3.13
Classifier: Programming Language :: Rust
Classifier: Topic :: Text Processing :: Markup :: HTML
Classifier: Topic :: Multimedia :: Graphics :: Graphics Conversion
Requires-Dist: pytest>=7.0 ; extra == 'dev'
Requires-Dist: pytest-asyncio>=0.21 ; extra == 'dev'
Provides-Extra: dev
Summary: High-fidelity HTML to PDF conversion using Chromium
Keywords: pdf,html,chromium,converter,render
License: AGPL-3.0
Requires-Python: >=3.9
Project-URL: Homepage, https://printwell.dev
Project-URL: Repository, https://github.com/printwell-dev/core
